gtmunit1/__init__.py
gtmunit1-0.12.4.dist-info/METADATA
gtmunit1-0.12.4.dist-info/WHEEL
gtmunit1-0.12.4.dist-info/top_level.txt
gtmunit1-0.12.4.dist-info/RECORD
