Metadata-Version: 2.1
Name: gtmunit1
Version: 0.12.4
Summary: Package 1 for Gigantum Client unit testing.
Home-page: https://github.com/gigantum/gigantum-client
Author: Gigantum
Author-email: hello@gigantum.com
License: MIT
Platform: UNKNOWN
Classifier: Development Status :: 4 - Beta
Classifier: Programming Language :: Python :: 3.6
Classifier: Programming Language :: Python :: 3.5
Classifier: Programming Language :: Python :: 2.7
